<?xml version="1.0" encoding="UTF-8" standalone="yes" ?>
<!DOCTYPE boost_serialization>
<boost_serialization signature="serialization::archive" version="4">
<object_list class_id="1" tracking_level="1" version="0" object_id="_0">
	<count>1</count>
	<item_version>1</item_version>
	<item class_id="0" tracking_level="0" version="1">
		<px class_id="189" tracking_level="1" version="0" object_id="_1">
			<ObjectId>TS_Euribor6M_YTD</ObjectId>
			<ClassName>qlTimeSeries</ClassName>
			<Dates class_id="202" tracking_level="0" version="0">
				<count>267</count>
				<item_version>0</item_version>
				<item class_id="203" tracking_level="0" version="0">
					<variant_ class_id="204" tracking_level="0" version="0">
						<which>1</which>
						<value>39090</value>
					</variant_>
				</item>
				<item>
					<variant_>
						<which>1</which>
						<value>39091</value>
					</variant_>
				</item>
				<item>
					<variant_>
						<which>1</which>
						<value>39092</value>
					</variant_>
				</item>
				<item>
					<variant_>
						<which>1</which>
						<value>39093</value>
					</variant_>
				</item>
				<item>
					<variant_>
						<which>1</which>
						<value>39094</value>
					</variant_>
				</item>
				<item>
					<variant_>
						<which>1</which>
						<value>39097</value>
					</variant_>
				</item>
				<item>
					<variant_>
						<which>1</which>
						<value>39098</value>
					</variant_>
				</item>
				<item>
					<variant_>
						<which>1</which>
						<value>39099</value>
					</variant_>
				</item>
				<item>
					<variant_>
						<which>1</which>
						<value>39100</value>
					</variant_>
				</item>
				<item>
					<variant_>
						<which>1</which>
						<value>39101</value>
					</variant_>
				</item>
				<item>
					<variant_>
						<which>1</which>
						<value>39104</value>
					</variant_>
				</item>
				<item>
					<variant_>
						<which>1</which>
						<value>39105</value>
					</variant_>
				</item>
				<item>
					<variant_>
						<which>1</which>
						<value>39106</value>
					</variant_>
				</item>
				<item>
					<variant_>
						<which>1</which>
						<value>39107</value>
					</variant_>
				</item>
				<item>
					<variant_>
						<which>1</which>
						<value>39108</value>
					</variant_>
				</item>
				<item>
					<variant_>
						<which>1</which>
						<value>39111</value>
					</variant_>
				</item>
				<item>
					<variant_>
						<which>1</which>
						<value>39112</value>
					</variant_>
				</item>
				<item>
					<variant_>
						<which>1</which>
						<value>39113</value>
					</variant_>
				</item>
				<item>
					<variant_>
						<which>1</which>
						<value>39114</value>
					</variant_>
				</item>
				<item>
					<variant_>
						<which>1</which>
						<value>39115</value>
					</variant_>
				</item>
				<item>
					<variant_>
						<which>1</which>
						<value>39118</value>
					</variant_>
				</item>
				<item>
					<variant_>
						<which>1</which>
						<value>39119</value>
					</variant_>
				</item>
				<item>
					<variant_>
						<which>1</which>
						<value>39120</value>
					</variant_>
				</item>
				<item>
					<variant_>
						<which>1</which>
						<value>39121</value>
					</variant_>
				</item>
				<item>
					<variant_>
						<which>1</which>
						<value>39122</value>
					</variant_>
				</item>
				<item>
					<variant_>
						<which>1</which>
						<value>39125</value>
					</variant_>
				</item>
				<item>
					<variant_>
						<which>1</which>
						<value>39126</value>
					</variant_>
				</item>
				<item>
					<variant_>
						<which>1</which>
						<value>39127</value>
					</variant_>
				</item>
				<item>
					<variant_>
						<which>1</which>
						<value>39128</value>
					</variant_>
				</item>
				<item>
					<variant_>
						<which>1</which>
						<value>39129</value>
					</variant_>
				</item>
				<item>
					<variant_>
						<which>1</which>
						<value>39132</value>
					</variant_>
				</item>
				<item>
					<variant_>
						<which>1</which>
						<value>39133</value>
					</variant_>
				</item>
				<item>
					<variant_>
						<which>1</which>
						<value>39134</value>
					</variant_>
				</item>
				<item>
					<variant_>
						<which>1</which>
						<value>39135</value>
					</variant_>
				</item>
				<item>
					<variant_>
						<which>1</which>
						<value>39136</value>
					</variant_>
				</item>
				<item>
					<variant_>
						<which>1</which>
						<value>39139</value>
					</variant_>
				</item>
				<item>
					<variant_>
						<which>1</which>
						<value>39140</value>
					</variant_>
				</item>
				<item>
					<variant_>
						<which>1</which>
						<value>39141</value>
					</variant_>
				</item>
				<item>
					<variant_>
						<which>1</which>
						<value>39142</value>
					</variant_>
				</item>
				<item>
					<variant_>
						<which>1</which>
						<value>39143</value>
					</variant_>
				</item>
				<item>
					<variant_>
						<which>1</which>
						<value>39146</value>
					</variant_>
				</item>
				<item>
					<variant_>
						<which>1</which>
						<value>39147</value>
					</variant_>
				</item>
				<item>
					<variant_>
						<which>1</which>
						<value>39148</value>
					</variant_>
				</item>
				<item>
					<variant_>
						<which>1</which>
						<value>39149</value>
					</variant_>
				</item>
				<item>
					<variant_>
						<which>1</which>
						<value>39150</value>
					</variant_>
				</item>
				<item>
					<variant_>
						<which>1</which>
						<value>39153</value>
					</variant_>
				</item>
				<item>
					<variant_>
						<which>1</which>
						<value>39154</value>
					</variant_>
				</item>
				<item>
					<variant_>
						<which>1</which>
						<value>39155</value>
					</variant_>
				</item>
				<item>
					<variant_>
						<which>1</which>
						<value>39156</value>
					</variant_>
				</item>
				<item>
					<variant_>
						<which>1</which>
						<value>39157</value>
					</variant_>
				</item>
				<item>
					<variant_>
						<which>1</which>
						<value>39160</value>
					</variant_>
				</item>
				<item>
					<variant_>
						<which>1</which>
						<value>39161</value>
					</variant_>
				</item>
				<item>
					<variant_>
						<which>1</which>
						<value>39162</value>
					</variant_>
				</item>
				<item>
					<variant_>
						<which>1</which>
						<value>39163</value>
					</variant_>
				</item>
				<item>
					<variant_>
						<which>1</which>
						<value>39164</value>
					</variant_>
				</item>
				<item>
					<variant_>
						<which>1</which>
						<value>39167</value>
					</variant_>
				</item>
				<item>
					<variant_>
						<which>1</which>
						<value>39168</value>
					</variant_>
				</item>
				<item>
					<variant_>
						<which>1</which>
						<value>39169</value>
					</variant_>
				</item>
				<item>
					<variant_>
						<which>1</which>
						<value>39170</value>
					</variant_>
				</item>
				<item>
					<variant_>
						<which>1</which>
						<value>39171</value>
					</variant_>
				</item>
				<item>
					<variant_>
						<which>1</which>
						<value>39174</value>
					</variant_>
				</item>
				<item>
					<variant_>
						<which>1</which>
						<value>39175</value>
					</variant_>
				</item>
				<item>
					<variant_>
						<which>1</which>
						<value>39176</value>
					</variant_>
				</item>
				<item>
					<variant_>
						<which>1</which>
						<value>39177</value>
					</variant_>
				</item>
				<item>
					<variant_>
						<which>1</which>
						<value>39182</value>
					</variant_>
				</item>
				<item>
					<variant_>
						<which>1</which>
						<value>39183</value>
					</variant_>
				</item>
				<item>
					<variant_>
						<which>1</which>
						<value>39184</value>
					</variant_>
				</item>
				<item>
					<variant_>
						<which>1</which>
						<value>39185</value>
					</variant_>
				</item>
				<item>
					<variant_>
						<which>1</which>
						<value>39188</value>
					</variant_>
				</item>
				<item>
					<variant_>
						<which>1</which>
						<value>39189</value>
					</variant_>
				</item>
				<item>
					<variant_>
						<which>1</which>
						<value>39190</value>
					</variant_>
				</item>
				<item>
					<variant_>
						<which>1</which>
						<value>39191</value>
					</variant_>
				</item>
				<item>
					<variant_>
						<which>1</which>
						<value>39192</value>
					</variant_>
				</item>
				<item>
					<variant_>
						<which>1</which>
						<value>39195</value>
					</variant_>
				</item>
				<item>
					<variant_>
						<which>1</which>
						<value>39196</value>
					</variant_>
				</item>
				<item>
					<variant_>
						<which>1</which>
						<value>39197</value>
					</variant_>
				</item>
				<item>
					<variant_>
						<which>1</which>
						<value>39198</value>
					</variant_>
				</item>
				<item>
					<variant_>
						<which>1</which>
						<value>39199</value>
					</variant_>
				</item>
				<item>
					<variant_>
						<which>1</which>
						<value>39202</value>
					</variant_>
				</item>
				<item>
					<variant_>
						<which>1</which>
						<value>39204</value>
					</variant_>
				</item>
				<item>
					<variant_>
						<which>1</which>
						<value>39205</value>
					</variant_>
				</item>
				<item>
					<variant_>
						<which>1</which>
						<value>39206</value>
					</variant_>
				</item>
				<item>
					<variant_>
						<which>1</which>
						<value>39209</value>
					</variant_>
				</item>
				<item>
					<variant_>
						<which>1</which>
						<value>39210</value>
					</variant_>
				</item>
				<item>
					<variant_>
						<which>1</which>
						<value>39211</value>
					</variant_>
				</item>
				<item>
					<variant_>
						<which>1</which>
						<value>39212</value>
					</variant_>
				</item>
				<item>
					<variant_>
						<which>1</which>
						<value>39213</value>
					</variant_>
				</item>
				<item>
					<variant_>
						<which>1</which>
						<value>39216</value>
					</variant_>
				</item>
				<item>
					<variant_>
						<which>1</which>
						<value>39217</value>
					</variant_>
				</item>
				<item>
					<variant_>
						<which>1</which>
						<value>39218</value>
					</variant_>
				</item>
				<item>
					<variant_>
						<which>1</which>
						<value>39219</value>
					</variant_>
				</item>
				<item>
					<variant_>
						<which>1</which>
						<value>39220</value>
					</variant_>
				</item>
				<item>
					<variant_>
						<which>1</which>
						<value>39223</value>
					</variant_>
				</item>
				<item>
					<variant_>
						<which>1</which>
						<value>39224</value>
					</variant_>
				</item>
				<item>
					<variant_>
						<which>1</which>
						<value>39225</value>
					</variant_>
				</item>
				<item>
					<variant_>
						<which>1</which>
						<value>39226</value>
					</variant_>
				</item>
				<item>
					<variant_>
						<which>1</which>
						<value>39227</value>
					</variant_>
				</item>
				<item>
					<variant_>
						<which>1</which>
						<value>39230</value>
					</variant_>
				</item>
				<item>
					<variant_>
						<which>1</which>
						<value>39231</value>
					</variant_>
				</item>
				<item>
					<variant_>
						<which>1</which>
						<value>39232</value>
					</variant_>
				</item>
				<item>
					<variant_>
						<which>1</which>
						<value>39233</value>
					</variant_>
				</item>
				<item>
					<variant_>
						<which>1</which>
						<value>39234</value>
					</variant_>
				</item>
				<item>
					<variant_>
						<which>1</which>
						<value>39237</value>
					</variant_>
				</item>
				<item>
					<variant_>
						<which>1</which>
						<value>39238</value>
					</variant_>
				</item>
				<item>
					<variant_>
						<which>1</which>
						<value>39239</value>
					</variant_>
				</item>
				<item>
					<variant_>
						<which>1</which>
						<value>39240</value>
					</variant_>
				</item>
				<item>
					<variant_>
						<which>1</which>
						<value>39241</value>
					</variant_>
				</item>
				<item>
					<variant_>
						<which>1</which>
						<value>39244</value>
					</variant_>
				</item>
				<item>
					<variant_>
						<which>1</which>
						<value>39245</value>
					</variant_>
				</item>
				<item>
					<variant_>
						<which>1</which>
						<value>39246</value>
					</variant_>
				</item>
				<item>
					<variant_>
						<which>1</which>
						<value>39247</value>
					</variant_>
				</item>
				<item>
					<variant_>
						<which>1</which>
						<value>39248</value>
					</variant_>
				</item>
				<item>
					<variant_>
						<which>1</which>
						<value>39251</value>
					</variant_>
				</item>
				<item>
					<variant_>
						<which>1</which>
						<value>39252</value>
					</variant_>
				</item>
				<item>
					<variant_>
						<which>1</which>
						<value>39253</value>
					</variant_>
				</item>
				<item>
					<variant_>
						<which>1</which>
						<value>39254</value>
					</variant_>
				</item>
				<item>
					<variant_>
						<which>1</which>
						<value>39255</value>
					</variant_>
				</item>
				<item>
					<variant_>
						<which>1</which>
						<value>39258</value>
					</variant_>
				</item>
				<item>
					<variant_>
						<which>1</which>
						<value>39259</value>
					</variant_>
				</item>
				<item>
					<variant_>
						<which>1</which>
						<value>39260</value>
					</variant_>
				</item>
				<item>
					<variant_>
						<which>1</which>
						<value>39261</value>
					</variant_>
				</item>
				<item>
					<variant_>
						<which>1</which>
						<value>39262</value>
					</variant_>
				</item>
				<item>
					<variant_>
						<which>1</which>
						<value>39265</value>
					</variant_>
				</item>
				<item>
					<variant_>
						<which>1</which>
						<value>39266</value>
					</variant_>
				</item>
				<item>
					<variant_>
						<which>1</which>
						<value>39267</value>
					</variant_>
				</item>
				<item>
					<variant_>
						<which>1</which>
						<value>39268</value>
					</variant_>
				</item>
				<item>
					<variant_>
						<which>1</which>
						<value>39269</value>
					</variant_>
				</item>
				<item>
					<variant_>
						<which>1</which>
						<value>39272</value>
					</variant_>
				</item>
				<item>
					<variant_>
						<which>1</which>
						<value>39273</value>
					</variant_>
				</item>
				<item>
					<variant_>
						<which>1</which>
						<value>39274</value>
					</variant_>
				</item>
				<item>
					<variant_>
						<which>1</which>
						<value>39275</value>
					</variant_>
				</item>
				<item>
					<variant_>
						<which>1</which>
						<value>39276</value>
					</variant_>
				</item>
				<item>
					<variant_>
						<which>1</which>
						<value>39279</value>
					</variant_>
				</item>
				<item>
					<variant_>
						<which>1</which>
						<value>39280</value>
					</variant_>
				</item>
				<item>
					<variant_>
						<which>1</which>
						<value>39281</value>
					</variant_>
				</item>
				<item>
					<variant_>
						<which>1</which>
						<value>39282</value>
					</variant_>
				</item>
				<item>
					<variant_>
						<which>1</which>
						<value>39283</value>
					</variant_>
				</item>
				<item>
					<variant_>
						<which>1</which>
						<value>39286</value>
					</variant_>
				</item>
				<item>
					<variant_>
						<which>1</which>
						<value>39287</value>
					</variant_>
				</item>
				<item>
					<variant_>
						<which>1</which>
						<value>39288</value>
					</variant_>
				</item>
				<item>
					<variant_>
						<which>1</which>
						<value>39289</value>
					</variant_>
				</item>
				<item>
					<variant_>
						<which>1</which>
						<value>39290</value>
					</variant_>
				</item>
				<item>
					<variant_>
						<which>1</which>
						<value>39293</value>
					</variant_>
				</item>
				<item>
					<variant_>
						<which>1</which>
						<value>39294</value>
					</variant_>
				</item>
				<item>
					<variant_>
						<which>1</which>
						<value>39295</value>
					</variant_>
				</item>
				<item>
					<variant_>
						<which>1</which>
						<value>39296</value>
					</variant_>
				</item>
				<item>
					<variant_>
						<which>1</which>
						<value>39297</value>
					</variant_>
				</item>
				<item>
					<variant_>
						<which>1</which>
						<value>39300</value>
					</variant_>
				</item>
				<item>
					<variant_>
						<which>1</which>
						<value>39301</value>
					</variant_>
				</item>
				<item>
					<variant_>
						<which>1</which>
						<value>39302</value>
					</variant_>
				</item>
				<item>
					<variant_>
						<which>1</which>
						<value>39303</value>
					</variant_>
				</item>
				<item>
					<variant_>
						<which>1</which>
						<value>39304</value>
					</variant_>
				</item>
				<item>
					<variant_>
						<which>1</which>
						<value>39307</value>
					</variant_>
				</item>
				<item>
					<variant_>
						<which>1</which>
						<value>39308</value>
					</variant_>
				</item>
				<item>
					<variant_>
						<which>1</which>
						<value>39309</value>
					</variant_>
				</item>
				<item>
					<variant_>
						<which>1</which>
						<value>39310</value>
					</variant_>
				</item>
				<item>
					<variant_>
						<which>1</which>
						<value>39311</value>
					</variant_>
				</item>
				<item>
					<variant_>
						<which>1</which>
						<value>39314</value>
					</variant_>
				</item>
				<item>
					<variant_>
						<which>1</which>
						<value>39315</value>
					</variant_>
				</item>
				<item>
					<variant_>
						<which>1</which>
						<value>39316</value>
					</variant_>
				</item>
				<item>
					<variant_>
						<which>1</which>
						<value>39317</value>
					</variant_>
				</item>
				<item>
					<variant_>
						<which>1</which>
						<value>39318</value>
					</variant_>
				</item>
				<item>
					<variant_>
						<which>1</which>
						<value>39321</value>
					</variant_>
				</item>
				<item>
					<variant_>
						<which>1</which>
						<value>39322</value>
					</variant_>
				</item>
				<item>
					<variant_>
						<which>1</which>
						<value>39323</value>
					</variant_>
				</item>
				<item>
					<variant_>
						<which>1</which>
						<value>39324</value>
					</variant_>
				</item>
				<item>
					<variant_>
						<which>1</which>
						<value>39325</value>
					</variant_>
				</item>
				<item>
					<variant_>
						<which>1</which>
						<value>39328</value>
					</variant_>
				</item>
				<item>
					<variant_>
						<which>1</which>
						<value>39329</value>
					</variant_>
				</item>
				<item>
					<variant_>
						<which>1</which>
						<value>39330</value>
					</variant_>
				</item>
				<item>
					<variant_>
						<which>1</which>
						<value>39331</value>
					</variant_>
				</item>
				<item>
					<variant_>
						<which>1</which>
						<value>39332</value>
					</variant_>
				</item>
				<item>
					<variant_>
						<which>1</which>
						<value>39335</value>
					</variant_>
				</item>
				<item>
					<variant_>
						<which>1</which>
						<value>39336</value>
					</variant_>
				</item>
				<item>
					<variant_>
						<which>1</which>
						<value>39337</value>
					</variant_>
				</item>
				<item>
					<variant_>
						<which>1</which>
						<value>39338</value>
					</variant_>
				</item>
				<item>
					<variant_>
						<which>1</which>
						<value>39339</value>
					</variant_>
				</item>
				<item>
					<variant_>
						<which>1</which>
						<value>39342</value>
					</variant_>
				</item>
				<item>
					<variant_>
						<which>1</which>
						<value>39343</value>
					</variant_>
				</item>
				<item>
					<variant_>
						<which>1</which>
						<value>39344</value>
					</variant_>
				</item>
				<item>
					<variant_>
						<which>1</which>
						<value>39345</value>
					</variant_>
				</item>
				<item>
					<variant_>
						<which>1</which>
						<value>39346</value>
					</variant_>
				</item>
				<item>
					<variant_>
						<which>1</which>
						<value>39349</value>
					</variant_>
				</item>
				<item>
					<variant_>
						<which>1</which>
						<value>39350</value>
					</variant_>
				</item>
				<item>
					<variant_>
						<which>1</which>
						<value>39351</value>
					</variant_>
				</item>
				<item>
					<variant_>
						<which>1</which>
						<value>39352</value>
					</variant_>
				</item>
				<item>
					<variant_>
						<which>1</which>
						<value>39353</value>
					</variant_>
				</item>
				<item>
					<variant_>
						<which>1</which>
						<value>39356</value>
					</variant_>
				</item>
				<item>
					<variant_>
						<which>1</which>
						<value>39357</value>
					</variant_>
				</item>
				<item>
					<variant_>
						<which>1</which>
						<value>39358</value>
					</variant_>
				</item>
				<item>
					<variant_>
						<which>1</which>
						<value>39359</value>
					</variant_>
				</item>
				<item>
					<variant_>
						<which>1</which>
						<value>39360</value>
					</variant_>
				</item>
				<item>
					<variant_>
						<which>1</which>
						<value>39363</value>
					</variant_>
				</item>
				<item>
					<variant_>
						<which>1</which>
						<value>39364</value>
					</variant_>
				</item>
				<item>
					<variant_>
						<which>1</which>
						<value>39365</value>
					</variant_>
				</item>
				<item>
					<variant_>
						<which>1</which>
						<value>39366</value>
					</variant_>
				</item>
				<item>
					<variant_>
						<which>1</which>
						<value>39367</value>
					</variant_>
				</item>
				<item>
					<variant_>
						<which>1</which>
						<value>39370</value>
					</variant_>
				</item>
				<item>
					<variant_>
						<which>1</which>
						<value>39371</value>
					</variant_>
				</item>
				<item>
					<variant_>
						<which>1</which>
						<value>39372</value>
					</variant_>
				</item>
				<item>
					<variant_>
						<which>1</which>
						<value>39373</value>
					</variant_>
				</item>
				<item>
					<variant_>
						<which>1</which>
						<value>39374</value>
					</variant_>
				</item>
				<item>
					<variant_>
						<which>1</which>
						<value>39377</value>
					</variant_>
				</item>
				<item>
					<variant_>
						<which>1</which>
						<value>39378</value>
					</variant_>
				</item>
				<item>
					<variant_>
						<which>1</which>
						<value>39379</value>
					</variant_>
				</item>
				<item>
					<variant_>
						<which>1</which>
						<value>39380</value>
					</variant_>
				</item>
				<item>
					<variant_>
						<which>1</which>
						<value>39381</value>
					</variant_>
				</item>
				<item>
					<variant_>
						<which>1</which>
						<value>39384</value>
					</variant_>
				</item>
				<item>
					<variant_>
						<which>1</which>
						<value>39385</value>
					</variant_>
				</item>
				<item>
					<variant_>
						<which>1</which>
						<value>39386</value>
					</variant_>
				</item>
				<item>
					<variant_>
						<which>1</which>
						<value>39387</value>
					</variant_>
				</item>
				<item>
					<variant_>
						<which>1</which>
						<value>39388</value>
					</variant_>
				</item>
				<item>
					<variant_>
						<which>1</which>
						<value>39391</value>
					</variant_>
				</item>
				<item>
					<variant_>
						<which>1</which>
						<value>39392</value>
					</variant_>
				</item>
				<item>
					<variant_>
						<which>1</which>
						<value>39393</value>
					</variant_>
				</item>
				<item>
					<variant_>
						<which>1</which>
						<value>39394</value>
					</variant_>
				</item>
				<item>
					<variant_>
						<which>1</which>
						<value>39395</value>
					</variant_>
				</item>
				<item>
					<variant_>
						<which>1</which>
						<value>39398</value>
					</variant_>
				</item>
				<item>
					<variant_>
						<which>1</which>
						<value>39399</value>
					</variant_>
				</item>
				<item>
					<variant_>
						<which>1</which>
						<value>39400</value>
					</variant_>
				</item>
				<item>
					<variant_>
						<which>1</which>
						<value>39401</value>
					</variant_>
				</item>
				<item>
					<variant_>
						<which>1</which>
						<value>39402</value>
					</variant_>
				</item>
				<item>
					<variant_>
						<which>1</which>
						<value>39405</value>
					</variant_>
				</item>
				<item>
					<variant_>
						<which>1</which>
						<value>39406</value>
					</variant_>
				</item>
				<item>
					<variant_>
						<which>1</which>
						<value>39407</value>
					</variant_>
				</item>
				<item>
					<variant_>
						<which>1</which>
						<value>39408</value>
					</variant_>
				</item>
				<item>
					<variant_>
						<which>1</which>
						<value>39409</value>
					</variant_>
				</item>
				<item>
					<variant_>
						<which>1</which>
						<value>39412</value>
					</variant_>
				</item>
				<item>
					<variant_>
						<which>1</which>
						<value>39413</value>
					</variant_>
				</item>
				<item>
					<variant_>
						<which>1</which>
						<value>39414</value>
					</variant_>
				</item>
				<item>
					<variant_>
						<which>1</which>
						<value>39415</value>
					</variant_>
				</item>
				<item>
					<variant_>
						<which>1</which>
						<value>39416</value>
					</variant_>
				</item>
				<item>
					<variant_>
						<which>1</which>
						<value>39419</value>
					</variant_>
				</item>
				<item>
					<variant_>
						<which>1</which>
						<value>39420</value>
					</variant_>
				</item>
				<item>
					<variant_>
						<which>1</which>
						<value>39421</value>
					</variant_>
				</item>
				<item>
					<variant_>
						<which>1</which>
						<value>39422</value>
					</variant_>
				</item>
				<item>
					<variant_>
						<which>1</which>
						<value>39423</value>
					</variant_>
				</item>
				<item>
					<variant_>
						<which>1</which>
						<value>39426</value>
					</variant_>
				</item>
				<item>
					<variant_>
						<which>1</which>
						<value>39427</value>
					</variant_>
				</item>
				<item>
					<variant_>
						<which>1</which>
						<value>39428</value>
					</variant_>
				</item>
				<item>
					<variant_>
						<which>1</which>
						<value>39429</value>
					</variant_>
				</item>
				<item>
					<variant_>
						<which>1</which>
						<value>39430</value>
					</variant_>
				</item>
				<item>
					<variant_>
						<which>1</which>
						<value>39433</value>
					</variant_>
				</item>
				<item>
					<variant_>
						<which>1</which>
						<value>39434</value>
					</variant_>
				</item>
				<item>
					<variant_>
						<which>1</which>
						<value>39435</value>
					</variant_>
				</item>
				<item>
					<variant_>
						<which>1</which>
						<value>39436</value>
					</variant_>
				</item>
				<item>
					<variant_>
						<which>1</which>
						<value>39437</value>
					</variant_>
				</item>
				<item>
					<variant_>
						<which>1</which>
						<value>39440</value>
					</variant_>
				</item>
				<item>
					<variant_>
						<which>1</which>
						<value>39443</value>
					</variant_>
				</item>
				<item>
					<variant_>
						<which>1</which>
						<value>39444</value>
					</variant_>
				</item>
				<item>
					<variant_>
						<which>1</which>
						<value>39447</value>
					</variant_>
				</item>
				<item>
					<variant_>
						<which>1</which>
						<value>39449</value>
					</variant_>
				</item>
				<item>
					<variant_>
						<which>1</which>
						<value>39450</value>
					</variant_>
				</item>
				<item>
					<variant_>
						<which>1</which>
						<value>39451</value>
					</variant_>
				</item>
				<item>
					<variant_>
						<which>1</which>
						<value>39454</value>
					</variant_>
				</item>
				<item>
					<variant_>
						<which>1</which>
						<value>39455</value>
					</variant_>
				</item>
				<item>
					<variant_>
						<which>1</which>
						<value>39456</value>
					</variant_>
				</item>
				<item>
					<variant_>
						<which>1</which>
						<value>39457</value>
					</variant_>
				</item>
				<item>
					<variant_>
						<which>1</which>
						<value>39458</value>
					</variant_>
				</item>
				<item>
					<variant_>
						<which>1</which>
						<value>39461</value>
					</variant_>
				</item>
				<item>
					<variant_>
						<which>1</which>
						<value>39462</value>
					</variant_>
				</item>
				<item>
					<variant_>
						<which>1</which>
						<value>39463</value>
					</variant_>
				</item>
				<item>
					<variant_>
						<which>1</which>
						<value>39464</value>
					</variant_>
				</item>
				<item>
					<variant_>
						<which>1</which>
						<value>39465</value>
					</variant_>
				</item>
				<item>
					<variant_>
						<which>1</which>
						<value>39468</value>
					</variant_>
				</item>
				<item>
					<variant_>
						<which>1</which>
						<value>39469</value>
					</variant_>
				</item>
				<item>
					<variant_>
						<which>1</which>
						<value>39470</value>
					</variant_>
				</item>
			</Dates>
			<Values>
				<count>267</count>
				<item_version>0</item_version>
				<item>
					<variant_>
						<which>1</which>
						<value>0.038740000000000004</value>
					</variant_>
				</item>
				<item>
					<variant_>
						<which>1</which>
						<value>0.038780000000000002</value>
					</variant_>
				</item>
				<item>
					<variant_>
						<which>1</which>
						<value>0.038849999999999996</value>
					</variant_>
				</item>
				<item>
					<variant_>
						<which>1</which>
						<value>0.039039999999999998</value>
					</variant_>
				</item>
				<item>
					<variant_>
						<which>1</which>
						<value>0.038759999999999996</value>
					</variant_>
				</item>
				<item>
					<variant_>
						<which>1</which>
						<value>0.038800000000000001</value>
					</variant_>
				</item>
				<item>
					<variant_>
						<which>1</which>
						<value>0.038830000000000003</value>
					</variant_>
				</item>
				<item>
					<variant_>
						<which>1</which>
						<value>0.038830000000000003</value>
					</variant_>
				</item>
				<item>
					<variant_>
						<which>1</which>
						<value>0.038879999999999998</value>
					</variant_>
				</item>
				<item>
					<variant_>
						<which>1</which>
						<value>0.038879999999999998</value>
					</variant_>
				</item>
				<item>
					<variant_>
						<which>1</which>
						<value>0.038929999999999999</value>
					</variant_>
				</item>
				<item>
					<variant_>
						<which>1</which>
						<value>0.038960000000000002</value>
					</variant_>
				</item>
				<item>
					<variant_>
						<which>1</which>
						<value>0.039060000000000004</value>
					</variant_>
				</item>
				<item>
					<variant_>
						<which>1</which>
						<value>0.039140000000000001</value>
					</variant_>
				</item>
				<item>
					<variant_>
						<which>1</which>
						<value>0.03916</value>
					</variant_>
				</item>
				<item>
					<variant_>
						<which>1</which>
						<value>0.039199999999999999</value>
					</variant_>
				</item>
				<item>
					<variant_>
						<which>1</which>
						<value>0.039209999999999995</value>
					</variant_>
				</item>
				<item>
					<variant_>
						<which>1</which>
						<value>0.039220000000000005</value>
					</variant_>
				</item>
				<item>
					<variant_>
						<which>1</which>
						<value>0.039230000000000001</value>
					</variant_>
				</item>
				<item>
					<variant_>
						<which>1</which>
						<value>0.039239999999999997</value>
					</variant_>
				</item>
				<item>
					<variant_>
						<which>1</which>
						<value>0.039079999999999997</value>
					</variant_>
				</item>
				<item>
					<variant_>
						<which>1</which>
						<value>0.039129999999999998</value>
					</variant_>
				</item>
				<item>
					<variant_>
						<which>1</which>
						<value>0.039199999999999999</value>
					</variant_>
				</item>
				<item>
					<variant_>
						<which>1</which>
						<value>0.039309999999999998</value>
					</variant_>
				</item>
				<item>
					<variant_>
						<which>1</which>
						<value>0.039410000000000001</value>
					</variant_>
				</item>
				<item>
					<variant_>
						<which>1</which>
						<value>0.039369999999999995</value>
					</variant_>
				</item>
				<item>
					<variant_>
						<which>1</which>
						<value>0.039449999999999999</value>
					</variant_>
				</item>
				<item>
					<variant_>
						<which>1</which>
						<value>0.039449999999999999</value>
					</variant_>
				</item>
				<item>
					<variant_>
						<which>1</which>
						<value>0.039460000000000002</value>
					</variant_>
				</item>
				<item>
					<variant_>
						<which>1</which>
						<value>0.039469999999999998</value>
					</variant_>
				</item>
				<item>
					<variant_>
						<which>1</which>
						<value>0.039529999999999996</value>
					</variant_>
				</item>
				<item>
					<variant_>
						<which>1</which>
						<value>0.039570000000000001</value>
					</variant_>
				</item>
				<item>
					<variant_>
						<which>1</which>
						<value>0.039609999999999999</value>
					</variant_>
				</item>
				<item>
					<variant_>
						<which>1</which>
						<value>0.039710000000000002</value>
					</variant_>
				</item>
				<item>
					<variant_>
						<which>1</which>
						<value>0.039730000000000001</value>
					</variant_>
				</item>
				<item>
					<variant_>
						<which>1</which>
						<value>0.039719999999999998</value>
					</variant_>
				</item>
				<item>
					<variant_>
						<which>1</which>
						<value>0.039730000000000001</value>
					</variant_>
				</item>
				<item>
					<variant_>
						<which>1</which>
						<value>0.039469999999999998</value>
					</variant_>
				</item>
				<item>
					<variant_>
						<which>1</which>
						<value>0.039599999999999996</value>
					</variant_>
				</item>
				<item>
					<variant_>
						<which>1</which>
						<value>0.039539999999999999</value>
					</variant_>
				</item>
				<item>
					<variant_>
						<which>1</which>
						<value>0.039230000000000001</value>
					</variant_>
				</item>
				<item>
					<variant_>
						<which>1</which>
						<value>0.03952</value>
					</variant_>
				</item>
				<item>
					<variant_>
						<which>1</which>
						<value>0.039599999999999996</value>
					</variant_>
				</item>
				<item>
					<variant_>
						<which>1</which>
						<value>0.039660000000000001</value>
					</variant_>
				</item>
				<item>
					<variant_>
						<which>1</which>
						<value>0.03986</value>
					</variant_>
				</item>
				<item>
					<variant_>
						<which>1</which>
						<value>0.040030000000000003</value>
					</variant_>
				</item>
				<item>
					<variant_>
						<which>1</which>
						<value>0.040010000000000004</value>
					</variant_>
				</item>
				<item>
					<variant_>
						<which>1</which>
						<value>0.039919999999999997</value>
					</variant_>
				</item>
				<item>
					<variant_>
						<which>1</which>
						<value>0.040030000000000003</value>
					</variant_>
				</item>
				<item>
					<variant_>
						<which>1</which>
						<value>0.040039999999999992</value>
					</variant_>
				</item>
				<item>
					<variant_>
						<which>1</which>
						<value>0.040090000000000001</value>
					</variant_>
				</item>
				<item>
					<variant_>
						<which>1</which>
						<value>0.040140000000000002</value>
					</variant_>
				</item>
				<item>
					<variant_>
						<which>1</which>
						<value>0.040099999999999997</value>
					</variant_>
				</item>
				<item>
					<variant_>
						<which>1</which>
						<value>0.040129999999999999</value>
					</variant_>
				</item>
				<item>
					<variant_>
						<which>1</which>
						<value>0.040140000000000002</value>
					</variant_>
				</item>
				<item>
					<variant_>
						<which>1</which>
						<value>0.040229999999999995</value>
					</variant_>
				</item>
				<item>
					<variant_>
						<which>1</which>
						<value>0.040250000000000001</value>
					</variant_>
				</item>
				<item>
					<variant_>
						<which>1</which>
						<value>0.040279999999999996</value>
					</variant_>
				</item>
				<item>
					<variant_>
						<which>1</which>
						<value>0.040359999999999993</value>
					</variant_>
				</item>
				<item>
					<variant_>
						<which>1</which>
						<value>0.040430000000000001</value>
					</variant_>
				</item>
				<item>
					<variant_>
						<which>1</which>
						<value>0.040480000000000002</value>
					</variant_>
				</item>
				<item>
					<variant_>
						<which>1</which>
						<value>0.040579999999999998</value>
					</variant_>
				</item>
				<item>
					<variant_>
						<which>1</which>
						<value>0.040689999999999997</value>
					</variant_>
				</item>
				<item>
					<variant_>
						<which>1</which>
						<value>0.040709999999999996</value>
					</variant_>
				</item>
				<item>
					<variant_>
						<which>1</which>
						<value>0.040780000000000004</value>
					</variant_>
				</item>
				<item>
					<variant_>
						<which>1</which>
						<value>0.040839999999999994</value>
					</variant_>
				</item>
				<item>
					<variant_>
						<which>1</which>
						<value>0.04095</value>
					</variant_>
				</item>
				<item>
					<variant_>
						<which>1</which>
						<value>0.040970000000000006</value>
					</variant_>
				</item>
				<item>
					<variant_>
						<which>1</which>
						<value>0.041009999999999998</value>
					</variant_>
				</item>
				<item>
					<variant_>
						<which>1</which>
						<value>0.041029999999999997</value>
					</variant_>
				</item>
				<item>
					<variant_>
						<which>1</which>
						<value>0.041020000000000001</value>
					</variant_>
				</item>
				<item>
					<variant_>
						<which>1</which>
						<value>0.041070000000000002</value>
					</variant_>
				</item>
				<item>
					<variant_>
						<which>1</which>
						<value>0.041079999999999998</value>
					</variant_>
				</item>
				<item>
					<variant_>
						<which>1</which>
						<value>0.041120000000000004</value>
					</variant_>
				</item>
				<item>
					<variant_>
						<which>1</which>
						<value>0.041120000000000004</value>
					</variant_>
				</item>
				<item>
					<variant_>
						<which>1</which>
						<value>0.041149999999999999</value>
					</variant_>
				</item>
				<item>
					<variant_>
						<which>1</which>
						<value>0.041230000000000003</value>
					</variant_>
				</item>
				<item>
					<variant_>
						<which>1</which>
						<value>0.041319999999999996</value>
					</variant_>
				</item>
				<item>
					<variant_>
						<which>1</which>
						<value>0.041349999999999998</value>
					</variant_>
				</item>
				<item>
					<variant_>
						<which>1</which>
						<value>0.041429999999999995</value>
					</variant_>
				</item>
				<item>
					<variant_>
						<which>1</which>
						<value>0.041529999999999997</value>
					</variant_>
				</item>
				<item>
					<variant_>
						<which>1</which>
						<value>0.041540000000000001</value>
					</variant_>
				</item>
				<item>
					<variant_>
						<which>1</which>
						<value>0.041589999999999995</value>
					</variant_>
				</item>
				<item>
					<variant_>
						<which>1</which>
						<value>0.041570000000000003</value>
					</variant_>
				</item>
				<item>
					<variant_>
						<which>1</which>
						<value>0.041609999999999994</value>
					</variant_>
				</item>
				<item>
					<variant_>
						<which>1</which>
						<value>0.041660000000000003</value>
					</variant_>
				</item>
				<item>
					<variant_>
						<which>1</which>
						<value>0.041599999999999998</value>
					</variant_>
				</item>
				<item>
					<variant_>
						<which>1</which>
						<value>0.04172</value>
					</variant_>
				</item>
				<item>
					<variant_>
						<which>1</which>
						<value>0.041799999999999997</value>
					</variant_>
				</item>
				<item>
					<variant_>
						<which>1</which>
						<value>0.041919999999999999</value>
					</variant_>
				</item>
				<item>
					<variant_>
						<which>1</which>
						<value>0.042099999999999999</value>
					</variant_>
				</item>
				<item>
					<variant_>
						<which>1</which>
						<value>0.042130000000000001</value>
					</variant_>
				</item>
				<item>
					<variant_>
						<which>1</which>
						<value>0.042140000000000004</value>
					</variant_>
				</item>
				<item>
					<variant_>
						<which>1</which>
						<value>0.042180000000000002</value>
					</variant_>
				</item>
				<item>
					<variant_>
						<which>1</which>
						<value>0.042279999999999998</value>
					</variant_>
				</item>
				<item>
					<variant_>
						<which>1</which>
						<value>0.042279999999999998</value>
					</variant_>
				</item>
				<item>
					<variant_>
						<which>1</which>
						<value>0.04233</value>
					</variant_>
				</item>
				<item>
					<variant_>
						<which>1</which>
						<value>0.0424</value>
					</variant_>
				</item>
				<item>
					<variant_>
						<which>1</which>
						<value>0.042439999999999999</value>
					</variant_>
				</item>
				<item>
					<variant_>
						<which>1</which>
						<value>0.042450000000000002</value>
					</variant_>
				</item>
				<item>
					<variant_>
						<which>1</which>
						<value>0.042549999999999998</value>
					</variant_>
				</item>
				<item>
					<variant_>
						<which>1</which>
						<value>0.04258</value>
					</variant_>
				</item>
				<item>
					<variant_>
						<which>1</which>
						<value>0.042590000000000003</value>
					</variant_>
				</item>
				<item>
					<variant_>
						<which>1</which>
						<value>0.042599999999999999</value>
					</variant_>
				</item>
				<item>
					<variant_>
						<which>1</which>
						<value>0.042640000000000004</value>
					</variant_>
				</item>
				<item>
					<variant_>
						<which>1</which>
						<value>0.042709999999999998</value>
					</variant_>
				</item>
				<item>
					<variant_>
						<which>1</which>
						<value>0.042689999999999999</value>
					</variant_>
				</item>
				<item>
					<variant_>
						<which>1</which>
						<value>0.042699999999999995</value>
					</variant_>
				</item>
				<item>
					<variant_>
						<which>1</which>
						<value>0.042709999999999998</value>
					</variant_>
				</item>
				<item>
					<variant_>
						<which>1</which>
						<value>0.042839999999999996</value>
					</variant_>
				</item>
				<item>
					<variant_>
						<which>1</which>
						<value>0.042830000000000007</value>
					</variant_>
				</item>
				<item>
					<variant_>
						<which>1</which>
						<value>0.042839999999999996</value>
					</variant_>
				</item>
				<item>
					<variant_>
						<which>1</which>
						<value>0.042839999999999996</value>
					</variant_>
				</item>
				<item>
					<variant_>
						<which>1</which>
						<value>0.042880000000000001</value>
					</variant_>
				</item>
				<item>
					<variant_>
						<which>1</which>
						<value>0.042809999999999994</value>
					</variant_>
				</item>
				<item>
					<variant_>
						<which>1</which>
						<value>0.04301</value>
					</variant_>
				</item>
				<item>
					<variant_>
						<which>1</which>
						<value>0.042979999999999997</value>
					</variant_>
				</item>
				<item>
					<variant_>
						<which>1</which>
						<value>0.042939999999999999</value>
					</variant_>
				</item>
				<item>
					<variant_>
						<which>1</which>
						<value>0.042950000000000002</value>
					</variant_>
				</item>
				<item>
					<variant_>
						<which>1</which>
						<value>0.042999999999999997</value>
					</variant_>
				</item>
				<item>
					<variant_>
						<which>1</which>
						<value>0.043129999999999995</value>
					</variant_>
				</item>
				<item>
					<variant_>
						<which>1</which>
						<value>0.043150000000000001</value>
					</variant_>
				</item>
				<item>
					<variant_>
						<which>1</which>
						<value>0.043159999999999997</value>
					</variant_>
				</item>
				<item>
					<variant_>
						<which>1</which>
						<value>0.043209999999999998</value>
					</variant_>
				</item>
				<item>
					<variant_>
						<which>1</which>
						<value>0.043259999999999993</value>
					</variant_>
				</item>
				<item>
					<variant_>
						<which>1</which>
						<value>0.043369999999999999</value>
					</variant_>
				</item>
				<item>
					<variant_>
						<which>1</which>
						<value>0.043470000000000002</value>
					</variant_>
				</item>
				<item>
					<variant_>
						<which>1</which>
						<value>0.043479999999999998</value>
					</variant_>
				</item>
				<item>
					<variant_>
						<which>1</which>
						<value>0.043499999999999997</value>
					</variant_>
				</item>
				<item>
					<variant_>
						<which>1</which>
						<value>0.043449999999999996</value>
					</variant_>
				</item>
				<item>
					<variant_>
						<which>1</which>
						<value>0.043560000000000001</value>
					</variant_>
				</item>
				<item>
					<variant_>
						<which>1</which>
						<value>0.043639999999999998</value>
					</variant_>
				</item>
				<item>
					<variant_>
						<which>1</which>
						<value>0.04367</value>
					</variant_>
				</item>
				<item>
					<variant_>
						<which>1</which>
						<value>0.043659999999999997</value>
					</variant_>
				</item>
				<item>
					<variant_>
						<which>1</which>
						<value>0.043659999999999997</value>
					</variant_>
				</item>
				<item>
					<variant_>
						<which>1</which>
						<value>0.043749999999999997</value>
					</variant_>
				</item>
				<item>
					<variant_>
						<which>1</which>
						<value>0.043769999999999996</value>
					</variant_>
				</item>
				<item>
					<variant_>
						<which>1</which>
						<value>0.04369</value>
					</variant_>
				</item>
				<item>
					<variant_>
						<which>1</which>
						<value>0.043769999999999996</value>
					</variant_>
				</item>
				<item>
					<variant_>
						<which>1</which>
						<value>0.04376</value>
					</variant_>
				</item>
				<item>
					<variant_>
						<which>1</which>
						<value>0.043840000000000004</value>
					</variant_>
				</item>
				<item>
					<variant_>
						<which>1</which>
						<value>0.043730000000000005</value>
					</variant_>
				</item>
				<item>
					<variant_>
						<which>1</which>
						<value>0.043659999999999997</value>
					</variant_>
				</item>
				<item>
					<variant_>
						<which>1</which>
						<value>0.043819999999999998</value>
					</variant_>
				</item>
				<item>
					<variant_>
						<which>1</which>
						<value>0.043710000000000006</value>
					</variant_>
				</item>
				<item>
					<variant_>
						<which>1</which>
						<value>0.04394</value>
					</variant_>
				</item>
				<item>
					<variant_>
						<which>1</which>
						<value>0.044069999999999998</value>
					</variant_>
				</item>
				<item>
					<variant_>
						<which>1</which>
						<value>0.044109999999999996</value>
					</variant_>
				</item>
				<item>
					<variant_>
						<which>1</which>
						<value>0.044310000000000002</value>
					</variant_>
				</item>
				<item>
					<variant_>
						<which>1</which>
						<value>0.04444</value>
					</variant_>
				</item>
				<item>
					<variant_>
						<which>1</which>
						<value>0.044770000000000004</value>
					</variant_>
				</item>
				<item>
					<variant_>
						<which>1</which>
						<value>0.045159999999999999</value>
					</variant_>
				</item>
				<item>
					<variant_>
						<which>1</which>
						<value>0.045650000000000003</value>
					</variant_>
				</item>
				<item>
					<variant_>
						<which>1</which>
						<value>0.045710000000000001</value>
					</variant_>
				</item>
				<item>
					<variant_>
						<which>1</which>
						<value>0.045739999999999996</value>
					</variant_>
				</item>
				<item>
					<variant_>
						<which>1</which>
						<value>0.046130000000000004</value>
					</variant_>
				</item>
				<item>
					<variant_>
						<which>1</which>
						<value>0.046529999999999995</value>
					</variant_>
				</item>
				<item>
					<variant_>
						<which>1</which>
						<value>0.046669999999999996</value>
					</variant_>
				</item>
				<item>
					<variant_>
						<which>1</which>
						<value>0.046699999999999998</value>
					</variant_>
				</item>
				<item>
					<variant_>
						<which>1</which>
						<value>0.046929999999999999</value>
					</variant_>
				</item>
				<item>
					<variant_>
						<which>1</which>
						<value>0.047469999999999998</value>
					</variant_>
				</item>
				<item>
					<variant_>
						<which>1</which>
						<value>0.047569999999999994</value>
					</variant_>
				</item>
				<item>
					<variant_>
						<which>1</which>
						<value>0.047449999999999999</value>
					</variant_>
				</item>
				<item>
					<variant_>
						<which>1</which>
						<value>0.047220000000000005</value>
					</variant_>
				</item>
				<item>
					<variant_>
						<which>1</which>
						<value>0.047270000000000006</value>
					</variant_>
				</item>
				<item>
					<variant_>
						<which>1</which>
						<value>0.047380000000000005</value>
					</variant_>
				</item>
				<item>
					<variant_>
						<which>1</which>
						<value>0.047640000000000002</value>
					</variant_>
				</item>
				<item>
					<variant_>
						<which>1</which>
						<value>0.047649999999999998</value>
					</variant_>
				</item>
				<item>
					<variant_>
						<which>1</which>
						<value>0.04777</value>
					</variant_>
				</item>
				<item>
					<variant_>
						<which>1</which>
						<value>0.04793</value>
					</variant_>
				</item>
				<item>
					<variant_>
						<which>1</which>
						<value>0.047739999999999998</value>
					</variant_>
				</item>
				<item>
					<variant_>
						<which>1</which>
						<value>0.047629999999999999</value>
					</variant_>
				</item>
				<item>
					<variant_>
						<which>1</which>
						<value>0.047530000000000003</value>
					</variant_>
				</item>
				<item>
					<variant_>
						<which>1</which>
						<value>0.047599999999999996</value>
					</variant_>
				</item>
				<item>
					<variant_>
						<which>1</which>
						<value>0.047619999999999996</value>
					</variant_>
				</item>
				<item>
					<variant_>
						<which>1</which>
						<value>0.047550000000000002</value>
					</variant_>
				</item>
				<item>
					<variant_>
						<which>1</which>
						<value>0.04734</value>
					</variant_>
				</item>
				<item>
					<variant_>
						<which>1</which>
						<value>0.047300000000000002</value>
					</variant_>
				</item>
				<item>
					<variant_>
						<which>1</which>
						<value>0.04734</value>
					</variant_>
				</item>
				<item>
					<variant_>
						<which>1</which>
						<value>0.047300000000000002</value>
					</variant_>
				</item>
				<item>
					<variant_>
						<which>1</which>
						<value>0.047220000000000005</value>
					</variant_>
				</item>
				<item>
					<variant_>
						<which>1</which>
						<value>0.047199999999999999</value>
					</variant_>
				</item>
				<item>
					<variant_>
						<which>1</which>
						<value>0.047359999999999999</value>
					</variant_>
				</item>
				<item>
					<variant_>
						<which>1</which>
						<value>0.047460000000000002</value>
					</variant_>
				</item>
				<item>
					<variant_>
						<which>1</which>
						<value>0.047500000000000001</value>
					</variant_>
				</item>
				<item>
					<variant_>
						<which>1</which>
						<value>0.047640000000000002</value>
					</variant_>
				</item>
				<item>
					<variant_>
						<which>1</which>
						<value>0.04759</value>
					</variant_>
				</item>
				<item>
					<variant_>
						<which>1</which>
						<value>0.047530000000000003</value>
					</variant_>
				</item>
				<item>
					<variant_>
						<which>1</which>
						<value>0.047530000000000003</value>
					</variant_>
				</item>
				<item>
					<variant_>
						<which>1</which>
						<value>0.047489999999999997</value>
					</variant_>
				</item>
				<item>
					<variant_>
						<which>1</which>
						<value>0.047359999999999999</value>
					</variant_>
				</item>
				<item>
					<variant_>
						<which>1</which>
						<value>0.047249999999999993</value>
					</variant_>
				</item>
				<item>
					<variant_>
						<which>1</which>
						<value>0.047230000000000001</value>
					</variant_>
				</item>
				<item>
					<variant_>
						<which>1</which>
						<value>0.047160000000000001</value>
					</variant_>
				</item>
				<item>
					<variant_>
						<which>1</which>
						<value>0.047039999999999998</value>
					</variant_>
				</item>
				<item>
					<variant_>
						<which>1</which>
						<value>0.046929999999999999</value>
					</variant_>
				</item>
				<item>
					<variant_>
						<which>1</which>
						<value>0.046529999999999995</value>
					</variant_>
				</item>
				<item>
					<variant_>
						<which>1</which>
						<value>0.046559999999999997</value>
					</variant_>
				</item>
				<item>
					<variant_>
						<which>1</which>
						<value>0.046509999999999996</value>
					</variant_>
				</item>
				<item>
					<variant_>
						<which>1</which>
						<value>0.046550000000000001</value>
					</variant_>
				</item>
				<item>
					<variant_>
						<which>1</which>
						<value>0.046519999999999999</value>
					</variant_>
				</item>
				<item>
					<variant_>
						<which>1</which>
						<value>0.046340000000000006</value>
					</variant_>
				</item>
				<item>
					<variant_>
						<which>1</which>
						<value>0.046089999999999999</value>
					</variant_>
				</item>
				<item>
					<variant_>
						<which>1</which>
						<value>0.046079999999999996</value>
					</variant_>
				</item>
				<item>
					<variant_>
						<which>1</which>
						<value>0.04598</value>
					</variant_>
				</item>
				<item>
					<variant_>
						<which>1</which>
						<value>0.045899999999999996</value>
					</variant_>
				</item>
				<item>
					<variant_>
						<which>1</which>
						<value>0.045899999999999996</value>
					</variant_>
				</item>
				<item>
					<variant_>
						<which>1</which>
						<value>0.04598</value>
					</variant_>
				</item>
				<item>
					<variant_>
						<which>1</which>
						<value>0.046059999999999997</value>
					</variant_>
				</item>
				<item>
					<variant_>
						<which>1</which>
						<value>0.046059999999999997</value>
					</variant_>
				</item>
				<item>
					<variant_>
						<which>1</which>
						<value>0.046180000000000006</value>
					</variant_>
				</item>
				<item>
					<variant_>
						<which>1</which>
						<value>0.046059999999999997</value>
					</variant_>
				</item>
				<item>
					<variant_>
						<which>1</which>
						<value>0.046010000000000002</value>
					</variant_>
				</item>
				<item>
					<variant_>
						<which>1</which>
						<value>0.045999999999999999</value>
					</variant_>
				</item>
				<item>
					<variant_>
						<which>1</which>
						<value>0.045970000000000004</value>
					</variant_>
				</item>
				<item>
					<variant_>
						<which>1</which>
						<value>0.045830000000000003</value>
					</variant_>
				</item>
				<item>
					<variant_>
						<which>1</which>
						<value>0.0458</value>
					</variant_>
				</item>
				<item>
					<variant_>
						<which>1</which>
						<value>0.045720000000000004</value>
					</variant_>
				</item>
				<item>
					<variant_>
						<which>1</which>
						<value>0.045730000000000007</value>
					</variant_>
				</item>
				<item>
					<variant_>
						<which>1</which>
						<value>0.045789999999999997</value>
					</variant_>
				</item>
				<item>
					<variant_>
						<which>1</which>
						<value>0.045860000000000005</value>
					</variant_>
				</item>
				<item>
					<variant_>
						<which>1</which>
						<value>0.045919999999999996</value>
					</variant_>
				</item>
				<item>
					<variant_>
						<which>1</which>
						<value>0.04614</value>
					</variant_>
				</item>
				<item>
					<variant_>
						<which>1</which>
						<value>0.046170000000000003</value>
					</variant_>
				</item>
				<item>
					<variant_>
						<which>1</which>
						<value>0.046310000000000004</value>
					</variant_>
				</item>
				<item>
					<variant_>
						<which>1</which>
						<value>0.046539999999999998</value>
					</variant_>
				</item>
				<item>
					<variant_>
						<which>1</which>
						<value>0.046689999999999995</value>
					</variant_>
				</item>
				<item>
					<variant_>
						<which>1</which>
						<value>0.046859999999999999</value>
					</variant_>
				</item>
				<item>
					<variant_>
						<which>1</which>
						<value>0.046929999999999999</value>
					</variant_>
				</item>
				<item>
					<variant_>
						<which>1</which>
						<value>0.047149999999999997</value>
					</variant_>
				</item>
				<item>
					<variant_>
						<which>1</which>
						<value>0.047370000000000002</value>
					</variant_>
				</item>
				<item>
					<variant_>
						<which>1</which>
						<value>0.047510000000000004</value>
					</variant_>
				</item>
				<item>
					<variant_>
						<which>1</which>
						<value>0.047750000000000001</value>
					</variant_>
				</item>
				<item>
					<variant_>
						<which>1</which>
						<value>0.04795</value>
					</variant_>
				</item>
				<item>
					<variant_>
						<which>1</which>
						<value>0.048010000000000004</value>
					</variant_>
				</item>
				<item>
					<variant_>
						<which>1</which>
						<value>0.048000000000000001</value>
					</variant_>
				</item>
				<item>
					<variant_>
						<which>1</which>
						<value>0.048390000000000002</value>
					</variant_>
				</item>
				<item>
					<variant_>
						<which>1</which>
						<value>0.048600000000000004</value>
					</variant_>
				</item>
				<item>
					<variant_>
						<which>1</which>
						<value>0.048809999999999999</value>
					</variant_>
				</item>
				<item>
					<variant_>
						<which>1</which>
						<value>0.049059999999999999</value>
					</variant_>
				</item>
				<item>
					<variant_>
						<which>1</which>
						<value>0.048979999999999996</value>
					</variant_>
				</item>
				<item>
					<variant_>
						<which>1</which>
						<value>0.049100000000000005</value>
					</variant_>
				</item>
				<item>
					<variant_>
						<which>1</which>
						<value>0.049169999999999998</value>
					</variant_>
				</item>
				<item>
					<variant_>
						<which>1</which>
						<value>0.048369999999999996</value>
					</variant_>
				</item>
				<item>
					<variant_>
						<which>1</which>
						<value>0.048170000000000004</value>
					</variant_>
				</item>
				<item>
					<variant_>
						<which>1</which>
						<value>0.047919999999999997</value>
					</variant_>
				</item>
				<item>
					<variant_>
						<which>1</which>
						<value>0.047809999999999998</value>
					</variant_>
				</item>
				<item>
					<variant_>
						<which>1</which>
						<value>0.047750000000000001</value>
					</variant_>
				</item>
				<item>
					<variant_>
						<which>1</which>
						<value>0.04768</value>
					</variant_>
				</item>
				<item>
					<variant_>
						<which>1</which>
						<value>0.047089999999999993</value>
					</variant_>
				</item>
				<item>
					<variant_>
						<which>1</which>
						<value>0.047070000000000001</value>
					</variant_>
				</item>
				<item>
					<variant_>
						<which>1</which>
						<value>0.047030000000000002</value>
					</variant_>
				</item>
				<item>
					<variant_>
						<which>1</which>
						<value>0.046780000000000002</value>
					</variant_>
				</item>
				<item>
					<variant_>
						<which>1</which>
						<value>0.046609999999999999</value>
					</variant_>
				</item>
				<item>
					<variant_>
						<which>1</which>
						<value>0.046500000000000007</value>
					</variant_>
				</item>
				<item>
					<variant_>
						<which>1</which>
						<value>0.046449999999999998</value>
					</variant_>
				</item>
				<item>
					<variant_>
						<which>1</which>
						<value>0.04641</value>
					</variant_>
				</item>
				<item>
					<variant_>
						<which>1</which>
						<value>0.046369999999999995</value>
					</variant_>
				</item>
				<item>
					<variant_>
						<which>1</which>
						<value>0.046269999999999999</value>
					</variant_>
				</item>
				<item>
					<variant_>
						<which>1</which>
						<value>0.045869999999999994</value>
					</variant_>
				</item>
				<item>
					<variant_>
						<which>1</which>
						<value>0.045690000000000001</value>
					</variant_>
				</item>
				<item>
					<variant_>
						<which>1</which>
						<value>0.045170000000000002</value>
					</variant_>
				</item>
				<item>
					<variant_>
						<which>1</which>
						<value>0.044539999999999996</value>
					</variant_>
				</item>
				<item>
					<variant_>
						<which>1</which>
						<value>0.044240000000000002</value>
					</variant_>
				</item>
				<item>
					<variant_>
						<which>1</which>
						<value>0.043899999999999995</value>
					</variant_>
				</item>
				<item>
					<variant_>
						<which>1</which>
						<value>0.043270000000000003</value>
					</variant_>
				</item>
				<item>
					<variant_>
						<which>1</which>
						<value>0.042930000000000003</value>
					</variant_>
				</item>
			</Values>
			<Permanent>1</Permanent>
		</px>
	</item>
</object_list>
</boost_serialization>
